aioartnet/__init__.py
aioartnet/client.py
aioartnet/console.py
aioartnet/events.py
aioartnet/listen.py
aioartnet/main.py
aioartnet/models.py
aioartnet/network.py
aioartnet/py.typed
aioartnet-0.2.1.dist-info/licenses/LICENSE
aioartnet-0.2.1.dist-info/METADATA
aioartnet-0.2.1.dist-info/WHEEL
aioartnet-0.2.1.dist-info/top_level.txt
aioartnet-0.2.1.dist-info/RECORD
