Metadata-Version: 2.4
Name: aioartnet
Version: 0.2.1
Summary: Pure Python asyncio connector to Art-Net DMX Universes
Author-email: Chris Shucksmith <chris@teaengineering.co.uk>
Project-URL: Homepage, https://github.com/TeaEngineering/aioartnet
Project-URL: Issues, https://github.com/TeaEngineering/aioartnet/issues
Classifier: Programming Language :: Python :: 3.10
Classifier: Programming Language :: Python :: 3.11
Classifier: Programming Language :: Python :: 3.12
Classifier: Programming Language :: Python :: 3.13
Classifier: License :: OSI Approved :: MIT License
Classifier: Framework :: AsyncIO
Classifier: Operating System :: OS Independent
Requires-Python: >=3.10
License-File: LICENSE
Dynamic: license-file
